pping/__init__.py
pping/packet.py
pping/result.py
pping/session.py
pping/utils.py
pping-0.0.9.dist-info/LICENSE
pping-0.0.9.dist-info/METADATA
pping-0.0.9.dist-info/WHEEL
pping-0.0.9.dist-info/top_level.txt
pping-0.0.9.dist-info/RECORD
