Metadata-Version: 2.1
Name: pping
Version: 0.0.9
Summary: ping in python
Home-page: https://github.com/JLMin/pping
Author: JLMin
License: MIT
Platform: UNKNOWN
Classifier: Development Status :: 4 - Beta
Classifier: License :: OSI Approved :: MIT License
Classifier: Programming Language :: Python :: 3
Requires-Python: >=3.6
License-File: LICENSE
